{
   "ИмяБилда":"Билд 8.3 OF",
   "ВерсияПлатформы":"8.3",
   "КаталогПоискаВерсииПлатформы":"C:\Program Files (x86)\1cv8",
   "СтрокаПодключенияКБазе":"ENTERPRISE /F.\..\Distr\v83ServiceBase /RunModeOrdinaryApplication",
   "ПутьКVanessaBehavior": ".\..\vanessa-behavior.epf",
   "КаталогФич": ".\..\features\Core\FeatureReader",
   "ВыполнитьСценарии": "Истина",
   "ДелатьОтчетВФорматеАллюр": "Истина",
   "КаталогOutputAllureБазовый": ".\..\distr\allurereport",
   "ЗавершитьРаботуСистемы": "Истина",
   "ДелатьЛогВыполненияСценариевВЖР": "Истина",
   "ВыгружатьСтатусВыполненияСценариевВФайл": "Истина",
   "СоздаватьПодкаталогВКаталогеAllureДляЭтогоБилда": "Истина",
   "ДобавлятьКИмениСценарияУловияВыгрузки": "Истина",
   "ПутьКФайлуДляВыгрузкиСтатусаВыполненияСценариев": ".\..\distr\BuildStatus.log",
   "ВыводитьСообщенияВФайл": ".\..\distr\Messages 8.3 OF.txt",
   "СписокТеговИсключение":[
   "IgnoreOnCIMainBuild",
   "IgnoreOnOFBuilds"
   ]
}